xxtea.cpython-314-x86_64-linux-android.so
xxtea-3.6.0.dist-info/licenses/LICENSE
xxtea-3.6.0.dist-info/METADATA
xxtea-3.6.0.dist-info/WHEEL
xxtea-3.6.0.dist-info/top_level.txt
xxtea-3.6.0.dist-info/RECORD
